KolejkaCommon-0.1.202310121859-nspkg.pth
kolejka/common/__init__.py
kolejka/common/__nonpath__.py
kolejka/common/cgroups.py
kolejka/common/config.py
kolejka/common/gpu.py
kolejka/common/http_socket.py
kolejka/common/images.py
kolejka/common/limits.py
kolejka/common/nvidia.py
kolejka/common/parse.py
kolejka/common/settings.py
kolejka/common/subprocess.py
kolejka/common/tags.py
kolejka/common/task.py
kolejka/common/test/__init__.py
kolejka/common/test/__nonpath__.py
kolejka/common/test/test_limits.py
KolejkaCommon-0.1.202310121859.dist-info/METADATA
KolejkaCommon-0.1.202310121859.dist-info/WHEEL
KolejkaCommon-0.1.202310121859.dist-info/entry_points.txt
KolejkaCommon-0.1.202310121859.dist-info/namespace_packages.txt
KolejkaCommon-0.1.202310121859.dist-info/top_level.txt
KolejkaCommon-0.1.202310121859.dist-info/RECORD
